ordeq_viz/__init__.py
ordeq_viz/_version.py
ordeq_viz/api.py
ordeq_viz/graph.py
ordeq_viz/py.typed
ordeq_viz/to_kedro_viz.py
ordeq_viz/to_mermaid.py
ordeq_viz/to_mermaid_md.py
ordeq_viz-1.2.1.dist-info/licenses/LICENSE
ordeq_viz-1.2.1.dist-info/METADATA
ordeq_viz-1.2.1.dist-info/WHEEL
ordeq_viz-1.2.1.dist-info/top_level.txt
ordeq_viz-1.2.1.dist-info/RECORD
