Metadata-Version: 2.4
Name: ordeq_viz
Version: 1.2.1
Summary: Visualization for Ordeq project
Author: Niels Neerhoff, Simon Brugman
Maintainer: Niels Neerhoff, Simon Brugman
License-Expression: MIT
Requires-Python: >=3.10
License-File: LICENSE
Requires-Dist: ordeq>=1.3.0
Dynamic: license-file
